odoo8_addon_account_banking_mandate-8.0.0.2.1-py2.7-nspkg.pth
odoo8_addon_account_banking_mandate-8.0.0.2.1.dist-info/DESCRIPTION.rst
odoo8_addon_account_banking_mandate-8.0.0.2.1.dist-info/METADATA
odoo8_addon_account_banking_mandate-8.0.0.2.1.dist-info/RECORD
odoo8_addon_account_banking_mandate-8.0.0.2.1.dist-info/WHEEL
odoo8_addon_account_banking_mandate-8.0.0.2.1.dist-info/metadata.json
odoo8_addon_account_banking_mandate-8.0.0.2.1.dist-info/namespace_packages.txt
odoo8_addon_account_banking_mandate-8.0.0.2.1.dist-info/top_level.txt
odoo_addons/account_banking_mandate/README.rst
odoo_addons/account_banking_mandate/__init__.py
odoo_addons/account_banking_mandate/__openerp__.py
odoo_addons/account_banking_mandate/data/mandate_reference_sequence.xml
odoo_addons/account_banking_mandate/i18n/am.po
odoo_addons/account_banking_mandate/i18n/ar.po
odoo_addons/account_banking_mandate/i18n/bg.po
odoo_addons/account_banking_mandate/i18n/bs.po
odoo_addons/account_banking_mandate/i18n/ca.po
odoo_addons/account_banking_mandate/i18n/ca_ES.po
odoo_addons/account_banking_mandate/i18n/cs.po
odoo_addons/account_banking_mandate/i18n/da.po
odoo_addons/account_banking_mandate/i18n/da_DK.po
odoo_addons/account_banking_mandate/i18n/de.po
odoo_addons/account_banking_mandate/i18n/el_GR.po
odoo_addons/account_banking_mandate/i18n/en_AU.po
odoo_addons/account_banking_mandate/i18n/en_GB.po
odoo_addons/account_banking_mandate/i18n/es.po
odoo_addons/account_banking_mandate/i18n/es_AR.po
odoo_addons/account_banking_mandate/i18n/es_CL.po
odoo_addons/account_banking_mandate/i18n/es_CO.po
odoo_addons/account_banking_mandate/i18n/es_CR.po
odoo_addons/account_banking_mandate/i18n/es_DO.po
odoo_addons/account_banking_mandate/i18n/es_EC.po
odoo_addons/account_banking_mandate/i18n/es_ES.po
odoo_addons/account_banking_mandate/i18n/es_MX.po
odoo_addons/account_banking_mandate/i18n/es_PE.po
odoo_addons/account_banking_mandate/i18n/es_PY.po
odoo_addons/account_banking_mandate/i18n/es_VE.po
odoo_addons/account_banking_mandate/i18n/et.po
odoo_addons/account_banking_mandate/i18n/eu.po
odoo_addons/account_banking_mandate/i18n/fa.po
odoo_addons/account_banking_mandate/i18n/fi.po
odoo_addons/account_banking_mandate/i18n/fr.po
odoo_addons/account_banking_mandate/i18n/fr_CA.po
odoo_addons/account_banking_mandate/i18n/fr_CH.po
odoo_addons/account_banking_mandate/i18n/fr_FR.po
odoo_addons/account_banking_mandate/i18n/gl.po
